{
  "slug": "mvp-planner",
  "displayName": "MVP Development Planner",
  "division": "DreamBizLaunch",
  "category": "product",
  "tier": "pro",
  "description": "Plans MVP development with feature prioritization and sprint planning.",
  "capabilities": [
    "Feature prioritization matrix",
    "User story generation",
    "Sprint planning tools",
    "Technical stack recommendations",
    "Budget estimation engine",
    "Launch readiness checklist",
    "Advanced analytics dashboard",
    "Priority email support",
    "API access",
    "Custom integrations",
    "Webhook notifications",
    "Data export (CSV/JSON)",
    "Scheduled automations",
    "Multi-user access",
    "Real-time monitoring dashboard",
    "Automated error recovery",
    "Cross-bot data sharing",
    "Version history tracking",
    "Performance benchmarking",
    "Compliance reporting",
    "Multi-region deployment",
    "Auto-scaling resources",
    "Encrypted data at rest",
    "SOC 2 Type II compliant"
  ],
  "revenueModel": "SaaS subscription",
  "targetUsers": "Product managers, technical founders",
  "priceRange": "$129/mo",
  "status": "active",
  "source": "DreamCo Empire OS",
  "version": "2.0"
}