{
  "slug": "telehealth-assistant",
  "displayName": "Telehealth Visit Assistant",
  "division": "DreamHealth",
  "category": "telehealth",
  "tier": "pro",
  "description": "Manages telehealth visit workflows including scheduling, consent, and follow-up.",
  "capabilities": [
    "Virtual visit scheduling",
    "Pre-visit questionnaire automation",
    "Consent capture workflow",
    "Visit summary generation",
    "Follow-up task creation",
    "Patient satisfaction scoring",
    "Advanced analytics dashboard",
    "Priority email support",
    "API access",
    "Custom integrations",
    "Webhook notifications",
    "Data export (CSV/JSON)",
    "Scheduled automations",
    "Multi-user access",
    "Real-time monitoring dashboard",
    "Automated error recovery",
    "Cross-bot data sharing",
    "Version history tracking",
    "Performance benchmarking",
    "Compliance reporting",
    "Multi-region deployment",
    "Auto-scaling resources",
    "Encrypted data at rest",
    "SOC 2 Type II compliant"
  ],
  "revenueModel": "SaaS subscription",
  "targetUsers": "Telehealth providers, primary care clinics",
  "priceRange": "$99/mo",
  "status": "active",
  "source": "DreamCo Empire OS",
  "version": "2.0"
}