{
  "schema": "dreamco.buddy_creator_studio.v1",
  "mission": "Let Buddy help users build games, 3D simulations, college courses, kids learning projects, music videos, apps, websites, and bot businesses with model choice, consent checks, and sandbox-first workflows.",
  "default_mode": "sandbox_first_owner_approval_for_publish_or_paid_actions",
  "workflows": [
    {
      "id": "college_3d_simulation_course",
      "label": "College 3D Simulation Course Builder",
      "outputs": [
        "syllabus",
        "module map",
        "lesson plan",
        "3D scene spec",
        "assessment rubric",
        "starter code",
        "accessibility checklist"
      ],
      "engines": [
        "Three.js",
        "React Three Fiber",
        "Unity export plan",
        "WebXR optional",
        "physics sandbox"
      ],
      "buddy_steps": [
        "collect learning objectives",
        "choose age/college level",
        "generate 3D concept map",
        "build browser prototype",
        "create quiz/lab/rubric",
        "run accessibility and safety review",
        "package for LMS or website"
      ]
    },
    {
      "id": "kids_voice_image_game_builder",
      "label": "Kids Voice/Image Game Builder",
      "outputs": [
        "guardian consent checklist",
        "kid-safe game design doc",
        "character sheet",
        "voice preference packet",
        "image asset plan",
        "playable prototype checklist"
      ],
      "engines": [
        "Three.js",
        "Phaser",
        "Canvas",
        "local browser speech synthesis",
        "local SVG fallback"
      ],
      "buddy_steps": [
        "collect parent/guardian approval requirements",
        "avoid real-person cloning unless consent proof exists",
        "create age-safe mechanics",
        "generate local preview assets",
        "test controls on desktop/mobile",
        "prepare export and share packet"
      ]
    },
    {
      "id": "music_video_and_simulation_studio",
      "label": "Music Video And Simulation Studio",
      "outputs": [
        "concept",
        "script",
        "shot list",
        "storyboard",
        "asset list",
        "voice rights packet",
        "video generation prompt pack",
        "edit timeline"
      ],
      "engines": [
        "Runway optional",
        "local storyboard",
        "image model choice",
        "voice model choice",
        "browser preview"
      ],
      "buddy_steps": [
        "collect rights-safe concept",
        "block artist/celebrity imitation",
        "draft scenes and prompts",
        "generate or request assets",
        "assemble review checklist",
        "prepare export plan"
      ]
    },
    {
      "id": "game_app_store_builder",
      "label": "Game/App Store Builder",
      "outputs": [
        "game design doc",
        "prototype route",
        "asset manifest",
        "monetization plan",
        "store listing draft",
        "test checklist"
      ],
      "engines": [
        "Phaser",
        "Three.js",
        "Vite",
        "PWA",
        "Capacitor export plan"
      ],
      "buddy_steps": [
        "define genre and platform",
        "create prototype",
        "wire local save/settings",
        "run playtest checklist",
        "draft store listing",
        "gate publishing behind approval"
      ]
    }
  ],
  "guardrails": [
    "No cloning real voices, faces, likenesses, or images without explicit written consent.",
    "No minor voice or likeness cloning.",
    "Always label AI-generated or AI-edited media.",
    "Public publishing, paid model calls, app store submissions, customer outreach, and payment actions require owner approval.",
    "Kids and education content must include age range, safety level, accessibility review, and parent/teacher notes."
  ],
  "generated_at": "2026-07-21T02:48:28.501275+00:00"
}
