{
  "schema": "master_bot_registry.v1",
  "updated_at": "2026-06-01T00:00:00Z",
  "bots": [
    {
      "id": "dreambuddy_core",
      "name": "DreamBuddy Core",
      "division": "DreamAgents",
      "status": "active",
      "version": "1.0.0",
      "monetization": {
        "enabled": true,
        "methods": [
          "affiliate",
          "lead_generation"
        ]
      },
      "safety": {
        "approval_required": false,
        "risk_level": "medium"
      },
      "capabilities": [
        {
          "intent": "add_todo",
          "enabled": true,
          "risk_level": "low",
          "approval_required": false,
          "division": "DreamAgents",
          "revenue_generating": false,
          "spends_money": false
        },
        {
          "intent": "list_todos",
          "enabled": true,
          "risk_level": "low",
          "approval_required": false,
          "division": "DreamAgents",
          "revenue_generating": false,
          "spends_money": false
        },
        {
          "intent": "complete_todo",
          "enabled": true,
          "risk_level": "low",
          "approval_required": false,
          "division": "DreamAgents",
          "revenue_generating": false,
          "spends_money": false
        },
        {
          "intent": "lead_generation",
          "enabled": true,
          "risk_level": "medium",
          "approval_required": true,
          "division": "DreamSalesPro",
          "revenue_generating": true,
          "spends_money": false
        },
        {
          "intent": "send_email",
          "enabled": true,
          "risk_level": "medium",
          "approval_required": true,
          "division": "DreamSalesPro",
          "revenue_generating": false,
          "spends_money": false
        },
        {
          "intent": "run_paid_campaign",
          "enabled": true,
          "risk_level": "high",
          "approval_required": true,
          "division": "DreamMarket",
          "revenue_generating": true,
          "spends_money": true
        }
      ]
    }
  ]
}
