{
  "slug": "meeting-notes",
  "displayName": "Meeting Notes Summarizer",
  "division": "DreamAdmin",
  "category": "meetings",
  "tier": "free",
  "description": "Summarizes meeting notes with action item extraction and follow-up tracking.",
  "capabilities": [
    "Meeting summary generation",
    "Action item extraction",
    "Follow-up reminder scheduling",
    "Attendee distribution tools",
    "Search and archive access",
    "Basic analytics",
    "Email support",
    "Community access",
    "Real-time monitoring dashboard",
    "Automated error recovery",
    "Cross-bot data sharing",
    "Version history tracking",
    "Performance benchmarking",
    "Compliance reporting",
    "Multi-region deployment",
    "Auto-scaling resources",
    "Encrypted data at rest",
    "SOC 2 Type II compliant"
  ],
  "revenueModel": "SaaS subscription",
  "targetUsers": "All office employees, meeting organizers",
  "priceRange": "$0",
  "status": "active",
  "source": "DreamCo Empire OS",
  "version": "2.0"
}