{
  "slug": "safety-mfg",
  "displayName": "Manufacturing Safety Manager",
  "division": "DreamProduction",
  "category": "safety",
  "tier": "enterprise",
  "description": "Manages manufacturing safety with LOTO compliance and incident investigation.",
  "capabilities": [
    "LOTO procedure management",
    "Incident investigation workflow",
    "Near-miss reporting system",
    "Safety observation tracking",
    "JSA documentation tools",
    "OSHA recordkeeping automation",
    "Advanced analytics dashboard",
    "Priority email support",
    "API access",
    "Custom integrations",
    "Webhook notifications",
    "Data export (CSV/JSON)",
    "Scheduled automations",
    "Multi-user access",
    "Dedicated account manager",
    "SLA guarantee (99.9%)",
    "Custom model fine-tuning",
    "SSO/SAML authentication",
    "Audit logging",
    "Role-based access control",
    "White-label options",
    "On-premise deployment option",
    "Real-time monitoring dashboard",
    "Automated error recovery",
    "Cross-bot data sharing",
    "Version history tracking",
    "Performance benchmarking",
    "Compliance reporting",
    "Multi-region deployment",
    "Auto-scaling resources",
    "Encrypted data at rest",
    "SOC 2 Type II compliant"
  ],
  "revenueModel": "Enterprise license",
  "targetUsers": "Safety managers, plant directors",
  "priceRange": "$599/mo",
  "status": "active",
  "source": "DreamCo Empire OS",
  "version": "2.0"
}